<?xml version="1.0" encoding="UTF-8"?>
<GenRun Id="synth_1" LaunchPart="xc7a35ticpg236-1L" LaunchTime="1670616019">
  <File Type="PA-TCL" Name="multipliers_delays.tcl"/>
  <File Type="RDS-PROPCONSTRS" Name="multipliers_delays_drc_synth.rpt"/>
  <File Type="REPORTS-TCL" Name="multipliers_delays_reports.tcl"/>
  <File Type="RDS-RDS" Name="multipliers_delays.vds"/>
  <File Type="RDS-UTIL" Name="multipliers_delays_utilization_synth.rpt"/>
  <File Type="RDS-UTIL-PB" Name="multipliers_delays_utilization_synth.pb"/>
  <File Type="RDS-DCP" Name="multipliers_delays.dcp"/>
  <File Type="VDS-TIMINGSUMMARY" Name="multipliers_delays_timing_summary_synth.rpt"/>
  <File Type="VDS-TIMING-PB" Name="multipliers_delays_timing_summary_synth.pb"/>
  <FileSet Name="sources" Type="DesignSrcs" RelSrcDir="$PSRCDIR/sources_1">
    <Filter Type="Srcs"/>
    <File Path="$PSRCDIR/sources_1/new/com_mult.v">
      <FileInfo>
        <Attr Name="UsedIn" Val="synthesis"/>
        <Attr Name="UsedIn" Val="implementation"/>
        <Attr Name="UsedIn" Val="simulation"/>
      </FileInfo>
    </File>
    <File Path="$PSRCDIR/sources_1/imports/ripple_carry_add/ripple_carry_add.srcs/sources_1/imports/sources_1/new/full_add.v">
      <FileInfo>
        <Attr Name="ImportPath" Val="$PPRDIR/../../Lab 7/ripple_carry_add/ripple_carry_add.srcs/sources_1/imports/sources_1/new/full_add.v"/>
        <Attr Name="ImportTime" Val="1669690814"/>
        <Attr Name="UsedIn" Val="synthesis"/>
        <Attr Name="UsedIn" Val="implementation"/>
        <Attr Name="UsedIn" Val="simulation"/>
      </FileInfo>
    </File>
    <File Path="$PSRCDIR/sources_1/imports/ripple_carry_add/ripple_carry_add.srcs/sources_1/imports/sources_1/imports/new/half_add.v">
      <FileInfo>
        <Attr Name="ImportPath" Val="$PPRDIR/../../Lab 7/ripple_carry_add/ripple_carry_add.srcs/sources_1/imports/sources_1/imports/new/half_add.v"/>
        <Attr Name="ImportTime" Val="1669688686"/>
        <Attr Name="UsedIn" Val="synthesis"/>
        <Attr Name="UsedIn" Val="implementation"/>
        <Attr Name="UsedIn" Val="simulation"/>
      </FileInfo>
    </File>
    <File Path="$PSRCDIR/sources_1/imports/ripple_carry_add/ripple_carry_add.srcs/sources_1/new/nbit_ripple_add.v">
      <FileInfo>
        <Attr Name="ImportPath" Val="$PPRDIR/../../Lab 7/ripple_carry_add/ripple_carry_add.srcs/sources_1/new/nbit_ripple_add.v"/>
        <Attr Name="ImportTime" Val="1670194224"/>
        <Attr Name="UsedIn" Val="synthesis"/>
        <Attr Name="UsedIn" Val="implementation"/>
        <Attr Name="UsedIn" Val="simulation"/>
      </FileInfo>
    </File>
    <File Path="$PSRCDIR/sources_1/new/multipliers_delays.v">
      <FileInfo>
        <Attr Name="UsedIn" Val="synthesis"/>
        <Attr Name="UsedIn" Val="implementation"/>
        <Attr Name="UsedIn" Val="simulation"/>
      </FileInfo>
    </File>
    <File Path="$PSRCDIR/sources_1/new/booth_mult.v">
      <FileInfo>
        <Attr Name="AutoDisabled" Val="1"/>
        <Attr Name="UsedIn" Val="synthesis"/>
        <Attr Name="UsedIn" Val="implementation"/>
        <Attr Name="UsedIn" Val="simulation"/>
      </FileInfo>
    </File>
    <File Path="$PSRCDIR/sources_1/new/array_block.v">
      <FileInfo>
        <Attr Name="AutoDisabled" Val="1"/>
        <Attr Name="UsedIn" Val="synthesis"/>
        <Attr Name="UsedIn" Val="implementation"/>
        <Attr Name="UsedIn" Val="simulation"/>
      </FileInfo>
    </File>
    <File Path="$PSRCDIR/sources_1/new/array_row.v">
      <FileInfo>
        <Attr Name="AutoDisabled" Val="1"/>
        <Attr Name="UsedIn" Val="synthesis"/>
        <Attr Name="UsedIn" Val="implementation"/>
        <Attr Name="UsedIn" Val="simulation"/>
      </FileInfo>
    </File>
    <File Path="$PSRCDIR/sources_1/new/array_com_mult.v">
      <FileInfo>
        <Attr Name="AutoDisabled" Val="1"/>
        <Attr Name="UsedIn" Val="synthesis"/>
        <Attr Name="UsedIn" Val="implementation"/>
        <Attr Name="UsedIn" Val="simulation"/>
      </FileInfo>
    </File>
    <File Path="$PSRCDIR/sources_1/imports/ripple_carry_add/ripple_carry_add.srcs/sources_1/imports/hex_to_7seg.srcs/sources_1/new/anode_driver.v">
      <FileInfo>
        <Attr Name="AutoDisabled" Val="1"/>
        <Attr Name="ImportPath" Val="$PPRDIR/../../Lab 7/ripple_carry_add/ripple_carry_add.srcs/sources_1/imports/hex_to_7seg.srcs/sources_1/new/anode_driver.v"/>
        <Attr Name="ImportTime" Val="1670188520"/>
        <Attr Name="UsedIn" Val="synthesis"/>
        <Attr Name="UsedIn" Val="implementation"/>
        <Attr Name="UsedIn" Val="simulation"/>
      </FileInfo>
    </File>
    <File Path="$PSRCDIR/sources_1/imports/ripple_carry_add/ripple_carry_add.srcs/sources_1/imports/hex_to_7seg.srcs/sources_1/new/clock_converter.v">
      <FileInfo>
        <Attr Name="AutoDisabled" Val="1"/>
        <Attr Name="ImportPath" Val="$PPRDIR/../../Lab 7/ripple_carry_add/ripple_carry_add.srcs/sources_1/imports/hex_to_7seg.srcs/sources_1/new/clock_converter.v"/>
        <Attr Name="ImportTime" Val="1670188520"/>
        <Attr Name="UsedIn" Val="synthesis"/>
        <Attr Name="UsedIn" Val="implementation"/>
        <Attr Name="UsedIn" Val="simulation"/>
      </FileInfo>
    </File>
    <File Path="$PSRCDIR/sources_1/imports/ripple_carry_add/ripple_carry_add.srcs/sources_1/imports/hex_to_7seg.srcs/sources_1/new/decoder_7seg.v">
      <FileInfo>
        <Attr Name="AutoDisabled" Val="1"/>
        <Attr Name="ImportPath" Val="$PPRDIR/../../Lab 7/ripple_carry_add/ripple_carry_add.srcs/sources_1/imports/hex_to_7seg.srcs/sources_1/new/decoder_7seg.v"/>
        <Attr Name="ImportTime" Val="1670188520"/>
        <Attr Name="UsedIn" Val="synthesis"/>
        <Attr Name="UsedIn" Val="implementation"/>
        <Attr Name="UsedIn" Val="simulation"/>
      </FileInfo>
    </File>
    <File Path="$PSRCDIR/sources_1/imports/ripple_carry_add/ripple_carry_add.srcs/sources_1/imports/hex_to_7seg.srcs/sources_1/new/hex_to_7seg.v">
      <FileInfo>
        <Attr Name="AutoDisabled" Val="1"/>
        <Attr Name="ImportPath" Val="$PPRDIR/../../Lab 7/ripple_carry_add/ripple_carry_add.srcs/sources_1/imports/hex_to_7seg.srcs/sources_1/new/hex_to_7seg.v"/>
        <Attr Name="ImportTime" Val="1670201208"/>
        <Attr Name="UsedIn" Val="synthesis"/>
        <Attr Name="UsedIn" Val="implementation"/>
        <Attr Name="UsedIn" Val="simulation"/>
      </FileInfo>
    </File>
    <File Path="$PSRCDIR/sources_1/imports/ripple_carry_add/ripple_carry_add.srcs/sources_1/imports/hex_to_7seg.srcs/sources_1/new/mux_4bit_4to1.v">
      <FileInfo>
        <Attr Name="AutoDisabled" Val="1"/>
        <Attr Name="ImportPath" Val="$PPRDIR/../../Lab 7/ripple_carry_add/ripple_carry_add.srcs/sources_1/imports/hex_to_7seg.srcs/sources_1/new/mux_4bit_4to1.v"/>
        <Attr Name="ImportTime" Val="1670188520"/>
        <Attr Name="UsedIn" Val="synthesis"/>
        <Attr Name="UsedIn" Val="implementation"/>
        <Attr Name="UsedIn" Val="simulation"/>
      </FileInfo>
    </File>
    <File Path="$PSRCDIR/sources_1/imports/ripple_carry_add/ripple_carry_add.srcs/sources_1/imports/hex_to_7seg.srcs/sources_1/imports/new/n_bit_count.v">
      <FileInfo>
        <Attr Name="AutoDisabled" Val="1"/>
        <Attr Name="ImportPath" Val="$PPRDIR/../../Lab 7/ripple_carry_add/ripple_carry_add.srcs/sources_1/imports/hex_to_7seg.srcs/sources_1/imports/new/n_bit_count.v"/>
        <Attr Name="ImportTime" Val="1670188476"/>
        <Attr Name="UsedIn" Val="synthesis"/>
        <Attr Name="UsedIn" Val="implementation"/>
        <Attr Name="UsedIn" Val="simulation"/>
      </FileInfo>
    </File>
    <File Path="$PSRCDIR/sources_1/new/board_com_mult.v">
      <FileInfo>
        <Attr Name="AutoDisabled" Val="1"/>
        <Attr Name="UsedIn" Val="synthesis"/>
        <Attr Name="UsedIn" Val="implementation"/>
        <Attr Name="UsedIn" Val="simulation"/>
      </FileInfo>
    </File>
    <Config>
      <Option Name="DesignMode" Val="RTL"/>
      <Option Name="TopModule" Val="multipliers_delays"/>
    </Config>
  </FileSet>
  <FileSet Name="constrs_in" Type="Constrs" RelSrcDir="$PSRCDIR/constrs_1">
    <Filter Type="Constrs"/>
    <File Path="$PSRCDIR/constrs_1/imports/Xilinx/Basys-3-Master.xdc">
      <FileInfo>
        <Attr Name="UserDisabled" Val="1"/>
        <Attr Name="ImportPath" Val="$PPRDIR/../../Basys-3-Master.xdc"/>
        <Attr Name="ImportTime" Val="1669749620"/>
        <Attr Name="UsedIn" Val="synthesis"/>
        <Attr Name="UsedIn" Val="implementation"/>
      </FileInfo>
    </File>
    <File Path="$PSRCDIR/constrs_1/imports/new/7seg.xdc">
      <FileInfo>
        <Attr Name="UserDisabled" Val="1"/>
        <Attr Name="ImportPath" Val="$PPRDIR/../../Lab 7/ripple_carry_add/ripple_carry_add.srcs/constrs_1/new/7seg.xdc"/>
        <Attr Name="ImportTime" Val="1670203806"/>
        <Attr Name="UsedIn" Val="synthesis"/>
        <Attr Name="UsedIn" Val="implementation"/>
      </FileInfo>
    </File>
    <File Path="$PSRCDIR/constrs_1/imports/new/pmod.xdc">
      <FileInfo>
        <Attr Name="ImportPath" Val="$PPRDIR/../../Lab 7/ripple_carry_add/ripple_carry_add.srcs/constrs_1/new/pmod.xdc"/>
        <Attr Name="ImportTime" Val="1670204130"/>
        <Attr Name="UsedIn" Val="synthesis"/>
        <Attr Name="UsedIn" Val="implementation"/>
      </FileInfo>
    </File>
    <Config>
      <Option Name="ConstrsType" Val="XDC"/>
    </Config>
  </FileSet>
  <FileSet Name="utils" Type="Utils" RelSrcDir="$PSRCDIR/utils_1">
    <Filter Type="Utils"/>
    <Config>
      <Option Name="TopAutoSet" Val="TRUE"/>
    </Config>
  </FileSet>
  <Strategy Version="1" Minor="2">
    <StratHandle Name="Vivado Synthesis Defaults" Flow="Vivado Synthesis 2019"/>
    <Step Id="synth_design"/>
  </Strategy>
</GenRun>
